{
  "id": "12355760",
  "name": "4.0.0",
  "description": "Notturno",
  "date": "2025-05-23",
  "version": "4.0.0",
  "module": "",
  "lastUpdated": 1748396422948,
  "type": "release",
  "_links": {
    "curies": [
      {
        "name": "int",
        "href": "https://www.danklco.com/api-docs/rels.html#{rel}",
        "templated": true
      },
      {
        "name": "jira",
        "href": "https://www.danklco.com/api-docs/rels.html#{rel}",
        "templated": true
      },
      {
        "name": "proj",
        "href": "https://www.danklco.com/api-docs/rels.html#{rel}",
        "templated": true
      }
    ],
    "self": {
      "href": "https://apis.danklco.com/apache-release-info/SYNCOPE/12355760"
    },
    "int:project": {
      "title": "The project containing this release",
      "href": "https://apis.danklco.com/apache-release-info/SYNCOPE"
    },
    "int:root": {
      "title": "The root of this API",
      "href": "https://apis.danklco.com/apache-release-info/"
    },
    "jira:release": {
      "title": "The release in ASF Jira",
      "href": "https://issues.apache.org/jira/browse/SYNCOPE/fixforversion/12355760"
    },
    "jira:project": {
      "title": "The project containing this release in ASF Jira",
      "href": "https://issues.apache.org/jira/projects/SYNCOPE"
    }
  },
  "releaseNotes": "Release Notes - Syncope - Version 4.0.0",
  "_embedded": {
    "int:issues": [
      {
        "issue": "SYNCOPE-1868",
        "title": "NPE when performing provision without changing password",
        "type": "Bug",
        "_links": {
          "curies": [
            {
              "name": "int",
              "href": "https://www.danklco.com/api-docs/rels.html#{rel}",
              "templated": true
            },
            {
              "name": "jira",
              "href": "https://www.danklco.com/api-docs/rels.html#{rel}",
              "templated": true
            },
            {
              "name": "proj",
              "href": "https://www.danklco.com/api-docs/rels.html#{rel}",
              "templated": true
            }
          ],
          "int:release": {
            "title": "The release containing this issue",
            "href": "https://apis.danklco.com/apache-release-info/SYNCOPE/12355760"
          },
          "int:project": {
            "title": "The project containing this issue",
            "href": "https://apis.danklco.com/apache-release-info/SYNCOPE"
          },
          "int:root": {
            "title": "The root of this API",
            "href": "https://apis.danklco.com/apache-release-info/"
          },
          "jira:issue": {
            "title": "The issue in ASF Jira",
            "href": "https://issues.apache.org/jira/browse/SYNCOPE-1868"
          },
          "jira:release": {
            "title": "The release containing this issue in ASF Jira",
            "href": "https://issues.apache.org/jira/browse/SYNCOPE/fixforversion/12355760"
          },
          "jira:project": {
            "title": "The project containing this issue in ASF Jira",
            "href": "https://issues.apache.org/jira/projects/SYNCOPE"
          }
        }
      },
      {
        "issue": "SYNCOPE-1871",
        "title": "Realm selection shows only one of allowed sub-trees",
        "type": "Bug",
        "_links": {
          "curies": [
            {
              "name": "int",
              "href": "https://www.danklco.com/api-docs/rels.html#{rel}",
              "templated": true
            },
            {
              "name": "jira",
              "href": "https://www.danklco.com/api-docs/rels.html#{rel}",
              "templated": true
            },
            {
              "name": "proj",
              "href": "https://www.danklco.com/api-docs/rels.html#{rel}",
              "templated": true
            }
          ],
          "int:release": {
            "title": "The release containing this issue",
            "href": "https://apis.danklco.com/apache-release-info/SYNCOPE/12355760"
          },
          "int:project": {
            "title": "The project containing this issue",
            "href": "https://apis.danklco.com/apache-release-info/SYNCOPE"
          },
          "int:root": {
            "title": "The root of this API",
            "href": "https://apis.danklco.com/apache-release-info/"
          },
          "jira:issue": {
            "title": "The issue in ASF Jira",
            "href": "https://issues.apache.org/jira/browse/SYNCOPE-1871"
          },
          "jira:release": {
            "title": "The release containing this issue in ASF Jira",
            "href": "https://issues.apache.org/jira/browse/SYNCOPE/fixforversion/12355760"
          },
          "jira:project": {
            "title": "The project containing this issue in ASF Jira",
            "href": "https://issues.apache.org/jira/projects/SYNCOPE"
          }
        }
      },
      {
        "issue": "SYNCOPE-1873",
        "title": "LocalDateTime fields not properly handled in BeanPanel",
        "type": "Bug",
        "_links": {
          "curies": [
            {
              "name": "int",
              "href": "https://www.danklco.com/api-docs/rels.html#{rel}",
              "templated": true
            },
            {
              "name": "jira",
              "href": "https://www.danklco.com/api-docs/rels.html#{rel}",
              "templated": true
            },
            {
              "name": "proj",
              "href": "https://www.danklco.com/api-docs/rels.html#{rel}",
              "templated": true
            }
          ],
          "int:release": {
            "title": "The release containing this issue",
            "href": "https://apis.danklco.com/apache-release-info/SYNCOPE/12355760"
          },
          "int:project": {
            "title": "The project containing this issue",
            "href": "https://apis.danklco.com/apache-release-info/SYNCOPE"
          },
          "int:root": {
            "title": "The root of this API",
            "href": "https://apis.danklco.com/apache-release-info/"
          },
          "jira:issue": {
            "title": "The issue in ASF Jira",
            "href": "https://issues.apache.org/jira/browse/SYNCOPE-1873"
          },
          "jira:release": {
            "title": "The release containing this issue in ASF Jira",
            "href": "https://issues.apache.org/jira/browse/SYNCOPE/fixforversion/12355760"
          },
          "jira:project": {
            "title": "The project containing this issue in ASF Jira",
            "href": "https://issues.apache.org/jira/projects/SYNCOPE"
          }
        }
      },
      {
        "issue": "SYNCOPE-1875",
        "title": "SAML delegated authentication: metadata keeps getting re-generated",
        "type": "Bug",
        "_links": {
          "curies": [
            {
              "name": "int",
              "href": "https://www.danklco.com/api-docs/rels.html#{rel}",
              "templated": true
            },
            {
              "name": "jira",
              "href": "https://www.danklco.com/api-docs/rels.html#{rel}",
              "templated": true
            },
            {
              "name": "proj",
              "href": "https://www.danklco.com/api-docs/rels.html#{rel}",
              "templated": true
            }
          ],
          "int:release": {
            "title": "The release containing this issue",
            "href": "https://apis.danklco.com/apache-release-info/SYNCOPE/12355760"
          },
          "int:project": {
            "title": "The project containing this issue",
            "href": "https://apis.danklco.com/apache-release-info/SYNCOPE"
          },
          "int:root": {
            "title": "The root of this API",
            "href": "https://apis.danklco.com/apache-release-info/"
          },
          "jira:issue": {
            "title": "The issue in ASF Jira",
            "href": "https://issues.apache.org/jira/browse/SYNCOPE-1875"
          },
          "jira:release": {
            "title": "The release containing this issue in ASF Jira",
            "href": "https://issues.apache.org/jira/browse/SYNCOPE/fixforversion/12355760"
          },
          "jira:project": {
            "title": "The project containing this issue in ASF Jira",
            "href": "https://issues.apache.org/jira/projects/SYNCOPE"
          }
        }
      },
      {
        "issue": "SYNCOPE-1878",
        "title": "Priority propagation failing with NOT_ATTEMPTED",
        "type": "Bug",
        "_links": {
          "curies": [
            {
              "name": "int",
              "href": "https://www.danklco.com/api-docs/rels.html#{rel}",
              "templated": true
            },
            {
              "name": "jira",
              "href": "https://www.danklco.com/api-docs/rels.html#{rel}",
              "templated": true
            },
            {
              "name": "proj",
              "href": "https://www.danklco.com/api-docs/rels.html#{rel}",
              "templated": true
            }
          ],
          "int:release": {
            "title": "The release containing this issue",
            "href": "https://apis.danklco.com/apache-release-info/SYNCOPE/12355760"
          },
          "int:project": {
            "title": "The project containing this issue",
            "href": "https://apis.danklco.com/apache-release-info/SYNCOPE"
          },
          "int:root": {
            "title": "The root of this API",
            "href": "https://apis.danklco.com/apache-release-info/"
          },
          "jira:issue": {
            "title": "The issue in ASF Jira",
            "href": "https://issues.apache.org/jira/browse/SYNCOPE-1878"
          },
          "jira:release": {
            "title": "The release containing this issue in ASF Jira",
            "href": "https://issues.apache.org/jira/browse/SYNCOPE/fixforversion/12355760"
          },
          "jira:project": {
            "title": "The project containing this issue in ASF Jira",
            "href": "https://issues.apache.org/jira/projects/SYNCOPE"
          }
        }
      },
      {
        "issue": "SYNCOPE-1879",
        "title": "Serialization error while auditing Pull data",
        "type": "Bug",
        "_links": {
          "curies": [
            {
              "name": "int",
              "href": "https://www.danklco.com/api-docs/rels.html#{rel}",
              "templated": true
            },
            {
              "name": "jira",
              "href": "https://www.danklco.com/api-docs/rels.html#{rel}",
              "templated": true
            },
            {
              "name": "proj",
              "href": "https://www.danklco.com/api-docs/rels.html#{rel}",
              "templated": true
            }
          ],
          "int:release": {
            "title": "The release containing this issue",
            "href": "https://apis.danklco.com/apache-release-info/SYNCOPE/12355760"
          },
          "int:project": {
            "title": "The project containing this issue",
            "href": "https://apis.danklco.com/apache-release-info/SYNCOPE"
          },
          "int:root": {
            "title": "The root of this API",
            "href": "https://apis.danklco.com/apache-release-info/"
          },
          "jira:issue": {
            "title": "The issue in ASF Jira",
            "href": "https://issues.apache.org/jira/browse/SYNCOPE-1879"
          },
          "jira:release": {
            "title": "The release containing this issue in ASF Jira",
            "href": "https://issues.apache.org/jira/browse/SYNCOPE/fixforversion/12355760"
          },
          "jira:project": {
            "title": "The project containing this issue in ASF Jira",
            "href": "https://issues.apache.org/jira/projects/SYNCOPE"
          }
        }
      },
      {
        "issue": "SYNCOPE-1881",
        "title": "WA: SP Metadata not fetched from Core",
        "type": "Bug",
        "_links": {
          "curies": [
            {
              "name": "int",
              "href": "https://www.danklco.com/api-docs/rels.html#{rel}",
              "templated": true
            },
            {
              "name": "jira",
              "href": "https://www.danklco.com/api-docs/rels.html#{rel}",
              "templated": true
            },
            {
              "name": "proj",
              "href": "https://www.danklco.com/api-docs/rels.html#{rel}",
              "templated": true
            }
          ],
          "int:release": {
            "title": "The release containing this issue",
            "href": "https://apis.danklco.com/apache-release-info/SYNCOPE/12355760"
          },
          "int:project": {
            "title": "The project containing this issue",
            "href": "https://apis.danklco.com/apache-release-info/SYNCOPE"
          },
          "int:root": {
            "title": "The root of this API",
            "href": "https://apis.danklco.com/apache-release-info/"
          },
          "jira:issue": {
            "title": "The issue in ASF Jira",
            "href": "https://issues.apache.org/jira/browse/SYNCOPE-1881"
          },
          "jira:release": {
            "title": "The release containing this issue in ASF Jira",
            "href": "https://issues.apache.org/jira/browse/SYNCOPE/fixforversion/12355760"
          },
          "jira:project": {
            "title": "The project containing this issue in ASF Jira",
            "href": "https://issues.apache.org/jira/projects/SYNCOPE"
          }
        }
      },
      {
        "issue": "SYNCOPE-1882",
        "title": "Multivalue dropdown attributes show additional empty selectable value",
        "type": "Bug",
        "_links": {
          "curies": [
            {
              "name": "int",
              "href": "https://www.danklco.com/api-docs/rels.html#{rel}",
              "templated": true
            },
            {
              "name": "jira",
              "href": "https://www.danklco.com/api-docs/rels.html#{rel}",
              "templated": true
            },
            {
              "name": "proj",
              "href": "https://www.danklco.com/api-docs/rels.html#{rel}",
              "templated": true
            }
          ],
          "int:release": {
            "title": "The release containing this issue",
            "href": "https://apis.danklco.com/apache-release-info/SYNCOPE/12355760"
          },
          "int:project": {
            "title": "The project containing this issue",
            "href": "https://apis.danklco.com/apache-release-info/SYNCOPE"
          },
          "int:root": {
            "title": "The root of this API",
            "href": "https://apis.danklco.com/apache-release-info/"
          },
          "jira:issue": {
            "title": "The issue in ASF Jira",
            "href": "https://issues.apache.org/jira/browse/SYNCOPE-1882"
          },
          "jira:release": {
            "title": "The release containing this issue in ASF Jira",
            "href": "https://issues.apache.org/jira/browse/SYNCOPE/fixforversion/12355760"
          },
          "jira:project": {
            "title": "The project containing this issue in ASF Jira",
            "href": "https://issues.apache.org/jira/projects/SYNCOPE"
          }
        }
      },
      {
        "issue": "SYNCOPE-1883",
        "title": "Google MFA authentication does not validate scratch codes",
        "type": "Bug",
        "_links": {
          "curies": [
            {
              "name": "int",
              "href": "https://www.danklco.com/api-docs/rels.html#{rel}",
              "templated": true
            },
            {
              "name": "jira",
              "href": "https://www.danklco.com/api-docs/rels.html#{rel}",
              "templated": true
            },
            {
              "name": "proj",
              "href": "https://www.danklco.com/api-docs/rels.html#{rel}",
              "templated": true
            }
          ],
          "int:release": {
            "title": "The release containing this issue",
            "href": "https://apis.danklco.com/apache-release-info/SYNCOPE/12355760"
          },
          "int:project": {
            "title": "The project containing this issue",
            "href": "https://apis.danklco.com/apache-release-info/SYNCOPE"
          },
          "int:root": {
            "title": "The root of this API",
            "href": "https://apis.danklco.com/apache-release-info/"
          },
          "jira:issue": {
            "title": "The issue in ASF Jira",
            "href": "https://issues.apache.org/jira/browse/SYNCOPE-1883"
          },
          "jira:release": {
            "title": "The release containing this issue in ASF Jira",
            "href": "https://issues.apache.org/jira/browse/SYNCOPE/fixforversion/12355760"
          },
          "jira:project": {
            "title": "The project containing this issue in ASF Jira",
            "href": "https://issues.apache.org/jira/projects/SYNCOPE"
          }
        }
      },
      {
        "issue": "SYNCOPE-1884",
        "title": "Errors with Encrypted plain values",
        "type": "Bug",
        "_links": {
          "curies": [
            {
              "name": "int",
              "href": "https://www.danklco.com/api-docs/rels.html#{rel}",
              "templated": true
            },
            {
              "name": "jira",
              "href": "https://www.danklco.com/api-docs/rels.html#{rel}",
              "templated": true
            },
            {
              "name": "proj",
              "href": "https://www.danklco.com/api-docs/rels.html#{rel}",
              "templated": true
            }
          ],
          "int:release": {
            "title": "The release containing this issue",
            "href": "https://apis.danklco.com/apache-release-info/SYNCOPE/12355760"
          },
          "int:project": {
            "title": "The project containing this issue",
            "href": "https://apis.danklco.com/apache-release-info/SYNCOPE"
          },
          "int:root": {
            "title": "The root of this API",
            "href": "https://apis.danklco.com/apache-release-info/"
          },
          "jira:issue": {
            "title": "The issue in ASF Jira",
            "href": "https://issues.apache.org/jira/browse/SYNCOPE-1884"
          },
          "jira:release": {
            "title": "The release containing this issue in ASF Jira",
            "href": "https://issues.apache.org/jira/browse/SYNCOPE/fixforversion/12355760"
          },
          "jira:project": {
            "title": "The project containing this issue in ASF Jira",
            "href": "https://issues.apache.org/jira/projects/SYNCOPE"
          }
        }
      },
      {
        "issue": "SYNCOPE-1617",
        "title": "Debezium support",
        "type": "New Feature",
        "_links": {
          "curies": [
            {
              "name": "int",
              "href": "https://www.danklco.com/api-docs/rels.html#{rel}",
              "templated": true
            },
            {
              "name": "jira",
              "href": "https://www.danklco.com/api-docs/rels.html#{rel}",
              "templated": true
            },
            {
              "name": "proj",
              "href": "https://www.danklco.com/api-docs/rels.html#{rel}",
              "templated": true
            }
          ],
          "int:release": {
            "title": "The release containing this issue",
            "href": "https://apis.danklco.com/apache-release-info/SYNCOPE/12355760"
          },
          "int:project": {
            "title": "The project containing this issue",
            "href": "https://apis.danklco.com/apache-release-info/SYNCOPE"
          },
          "int:root": {
            "title": "The root of this API",
            "href": "https://apis.danklco.com/apache-release-info/"
          },
          "jira:issue": {
            "title": "The issue in ASF Jira",
            "href": "https://issues.apache.org/jira/browse/SYNCOPE-1617"
          },
          "jira:release": {
            "title": "The release containing this issue in ASF Jira",
            "href": "https://issues.apache.org/jira/browse/SYNCOPE/fixforversion/12355760"
          },
          "jira:project": {
            "title": "The project containing this issue in ASF Jira",
            "href": "https://issues.apache.org/jira/projects/SYNCOPE"
          }
        }
      },
      {
        "issue": "SYNCOPE-1861",
        "title": "OpenLDAP Sync Replication support",
        "type": "New Feature",
        "_links": {
          "curies": [
            {
              "name": "int",
              "href": "https://www.danklco.com/api-docs/rels.html#{rel}",
              "templated": true
            },
            {
              "name": "jira",
              "href": "https://www.danklco.com/api-docs/rels.html#{rel}",
              "templated": true
            },
            {
              "name": "proj",
              "href": "https://www.danklco.com/api-docs/rels.html#{rel}",
              "templated": true
            }
          ],
          "int:release": {
            "title": "The release containing this issue",
            "href": "https://apis.danklco.com/apache-release-info/SYNCOPE/12355760"
          },
          "int:project": {
            "title": "The project containing this issue",
            "href": "https://apis.danklco.com/apache-release-info/SYNCOPE"
          },
          "int:root": {
            "title": "The root of this API",
            "href": "https://apis.danklco.com/apache-release-info/"
          },
          "jira:issue": {
            "title": "The issue in ASF Jira",
            "href": "https://issues.apache.org/jira/browse/SYNCOPE-1861"
          },
          "jira:release": {
            "title": "The release containing this issue in ASF Jira",
            "href": "https://issues.apache.org/jira/browse/SYNCOPE/fixforversion/12355760"
          },
          "jira:project": {
            "title": "The project containing this issue in ASF Jira",
            "href": "https://issues.apache.org/jira/projects/SYNCOPE"
          }
        }
      },
      {
        "issue": "SYNCOPE-1874",
        "title": "Realm attributes",
        "type": "New Feature",
        "_links": {
          "curies": [
            {
              "name": "int",
              "href": "https://www.danklco.com/api-docs/rels.html#{rel}",
              "templated": true
            },
            {
              "name": "jira",
              "href": "https://www.danklco.com/api-docs/rels.html#{rel}",
              "templated": true
            },
            {
              "name": "proj",
              "href": "https://www.danklco.com/api-docs/rels.html#{rel}",
              "templated": true
            }
          ],
          "int:release": {
            "title": "The release containing this issue",
            "href": "https://apis.danklco.com/apache-release-info/SYNCOPE/12355760"
          },
          "int:project": {
            "title": "The project containing this issue",
            "href": "https://apis.danklco.com/apache-release-info/SYNCOPE"
          },
          "int:root": {
            "title": "The root of this API",
            "href": "https://apis.danklco.com/apache-release-info/"
          },
          "jira:issue": {
            "title": "The issue in ASF Jira",
            "href": "https://issues.apache.org/jira/browse/SYNCOPE-1874"
          },
          "jira:release": {
            "title": "The release containing this issue in ASF Jira",
            "href": "https://issues.apache.org/jira/browse/SYNCOPE/fixforversion/12355760"
          },
          "jira:project": {
            "title": "The project containing this issue in ASF Jira",
            "href": "https://issues.apache.org/jira/projects/SYNCOPE"
          }
        }
      },
      {
        "issue": "SYNCOPE-1621",
        "title": "Allow export for individual items in XML",
        "type": "Improvement",
        "_links": {
          "curies": [
            {
              "name": "int",
              "href": "https://www.danklco.com/api-docs/rels.html#{rel}",
              "templated": true
            },
            {
              "name": "jira",
              "href": "https://www.danklco.com/api-docs/rels.html#{rel}",
              "templated": true
            },
            {
              "name": "proj",
              "href": "https://www.danklco.com/api-docs/rels.html#{rel}",
              "templated": true
            }
          ],
          "int:release": {
            "title": "The release containing this issue",
            "href": "https://apis.danklco.com/apache-release-info/SYNCOPE/12355760"
          },
          "int:project": {
            "title": "The project containing this issue",
            "href": "https://apis.danklco.com/apache-release-info/SYNCOPE"
          },
          "int:root": {
            "title": "The root of this API",
            "href": "https://apis.danklco.com/apache-release-info/"
          },
          "jira:issue": {
            "title": "The issue in ASF Jira",
            "href": "https://issues.apache.org/jira/browse/SYNCOPE-1621"
          },
          "jira:release": {
            "title": "The release containing this issue in ASF Jira",
            "href": "https://issues.apache.org/jira/browse/SYNCOPE/fixforversion/12355760"
          },
          "jira:project": {
            "title": "The project containing this issue in ASF Jira",
            "href": "https://issues.apache.org/jira/projects/SYNCOPE"
          }
        }
      },
      {
        "issue": "SYNCOPE-1841",
        "title": "Read-only multi value schema must not show new and delete button",
        "type": "Improvement",
        "_links": {
          "curies": [
            {
              "name": "int",
              "href": "https://www.danklco.com/api-docs/rels.html#{rel}",
              "templated": true
            },
            {
              "name": "jira",
              "href": "https://www.danklco.com/api-docs/rels.html#{rel}",
              "templated": true
            },
            {
              "name": "proj",
              "href": "https://www.danklco.com/api-docs/rels.html#{rel}",
              "templated": true
            }
          ],
          "int:release": {
            "title": "The release containing this issue",
            "href": "https://apis.danklco.com/apache-release-info/SYNCOPE/12355760"
          },
          "int:project": {
            "title": "The project containing this issue",
            "href": "https://apis.danklco.com/apache-release-info/SYNCOPE"
          },
          "int:root": {
            "title": "The root of this API",
            "href": "https://apis.danklco.com/apache-release-info/"
          },
          "jira:issue": {
            "title": "The issue in ASF Jira",
            "href": "https://issues.apache.org/jira/browse/SYNCOPE-1841"
          },
          "jira:release": {
            "title": "The release containing this issue in ASF Jira",
            "href": "https://issues.apache.org/jira/browse/SYNCOPE/fixforversion/12355760"
          },
          "jira:project": {
            "title": "The project containing this issue in ASF Jira",
            "href": "https://issues.apache.org/jira/projects/SYNCOPE"
          }
        }
      },
      {
        "issue": "SYNCOPE-1869",
        "title": "Support evaluation order for client apps",
        "type": "Improvement",
        "_links": {
          "curies": [
            {
              "name": "int",
              "href": "https://www.danklco.com/api-docs/rels.html#{rel}",
              "templated": true
            },
            {
              "name": "jira",
              "href": "https://www.danklco.com/api-docs/rels.html#{rel}",
              "templated": true
            },
            {
              "name": "proj",
              "href": "https://www.danklco.com/api-docs/rels.html#{rel}",
              "templated": true
            }
          ],
          "int:release": {
            "title": "The release containing this issue",
            "href": "https://apis.danklco.com/apache-release-info/SYNCOPE/12355760"
          },
          "int:project": {
            "title": "The project containing this issue",
            "href": "https://apis.danklco.com/apache-release-info/SYNCOPE"
          },
          "int:root": {
            "title": "The root of this API",
            "href": "https://apis.danklco.com/apache-release-info/"
          },
          "jira:issue": {
            "title": "The issue in ASF Jira",
            "href": "https://issues.apache.org/jira/browse/SYNCOPE-1869"
          },
          "jira:release": {
            "title": "The release containing this issue in ASF Jira",
            "href": "https://issues.apache.org/jira/browse/SYNCOPE/fixforversion/12355760"
          },
          "jira:project": {
            "title": "The project containing this issue in ASF Jira",
            "href": "https://issues.apache.org/jira/projects/SYNCOPE"
          }
        }
      },
      {
        "issue": "SYNCOPE-1870",
        "title": "Generic exception handling (RestServiceExceptionMapper)",
        "type": "Improvement",
        "_links": {
          "curies": [
            {
              "name": "int",
              "href": "https://www.danklco.com/api-docs/rels.html#{rel}",
              "templated": true
            },
            {
              "name": "jira",
              "href": "https://www.danklco.com/api-docs/rels.html#{rel}",
              "templated": true
            },
            {
              "name": "proj",
              "href": "https://www.danklco.com/api-docs/rels.html#{rel}",
              "templated": true
            }
          ],
          "int:release": {
            "title": "The release containing this issue",
            "href": "https://apis.danklco.com/apache-release-info/SYNCOPE/12355760"
          },
          "int:project": {
            "title": "The project containing this issue",
            "href": "https://apis.danklco.com/apache-release-info/SYNCOPE"
          },
          "int:root": {
            "title": "The root of this API",
            "href": "https://apis.danklco.com/apache-release-info/"
          },
          "jira:issue": {
            "title": "The issue in ASF Jira",
            "href": "https://issues.apache.org/jira/browse/SYNCOPE-1870"
          },
          "jira:release": {
            "title": "The release containing this issue in ASF Jira",
            "href": "https://issues.apache.org/jira/browse/SYNCOPE/fixforversion/12355760"
          },
          "jira:project": {
            "title": "The project containing this issue in ASF Jira",
            "href": "https://issues.apache.org/jira/projects/SYNCOPE"
          }
        }
      },
      {
        "issue": "SYNCOPE-1872",
        "title": "Allow setting of force execution for MFA authentication",
        "type": "Improvement",
        "_links": {
          "curies": [
            {
              "name": "int",
              "href": "https://www.danklco.com/api-docs/rels.html#{rel}",
              "templated": true
            },
            {
              "name": "jira",
              "href": "https://www.danklco.com/api-docs/rels.html#{rel}",
              "templated": true
            },
            {
              "name": "proj",
              "href": "https://www.danklco.com/api-docs/rels.html#{rel}",
              "templated": true
            }
          ],
          "int:release": {
            "title": "The release containing this issue",
            "href": "https://apis.danklco.com/apache-release-info/SYNCOPE/12355760"
          },
          "int:project": {
            "title": "The project containing this issue",
            "href": "https://apis.danklco.com/apache-release-info/SYNCOPE"
          },
          "int:root": {
            "title": "The root of this API",
            "href": "https://apis.danklco.com/apache-release-info/"
          },
          "jira:issue": {
            "title": "The issue in ASF Jira",
            "href": "https://issues.apache.org/jira/browse/SYNCOPE-1872"
          },
          "jira:release": {
            "title": "The release containing this issue in ASF Jira",
            "href": "https://issues.apache.org/jira/browse/SYNCOPE/fixforversion/12355760"
          },
          "jira:project": {
            "title": "The project containing this issue in ASF Jira",
            "href": "https://issues.apache.org/jira/projects/SYNCOPE"
          }
        }
      },
      {
        "issue": "SYNCOPE-1880",
        "title": "SCIM endpoints ignore the Prefer header",
        "type": "Improvement",
        "_links": {
          "curies": [
            {
              "name": "int",
              "href": "https://www.danklco.com/api-docs/rels.html#{rel}",
              "templated": true
            },
            {
              "name": "jira",
              "href": "https://www.danklco.com/api-docs/rels.html#{rel}",
              "templated": true
            },
            {
              "name": "proj",
              "href": "https://www.danklco.com/api-docs/rels.html#{rel}",
              "templated": true
            }
          ],
          "int:release": {
            "title": "The release containing this issue",
            "href": "https://apis.danklco.com/apache-release-info/SYNCOPE/12355760"
          },
          "int:project": {
            "title": "The project containing this issue",
            "href": "https://apis.danklco.com/apache-release-info/SYNCOPE"
          },
          "int:root": {
            "title": "The root of this API",
            "href": "https://apis.danklco.com/apache-release-info/"
          },
          "jira:issue": {
            "title": "The issue in ASF Jira",
            "href": "https://issues.apache.org/jira/browse/SYNCOPE-1880"
          },
          "jira:release": {
            "title": "The release containing this issue in ASF Jira",
            "href": "https://issues.apache.org/jira/browse/SYNCOPE/fixforversion/12355760"
          },
          "jira:project": {
            "title": "The project containing this issue in ASF Jira",
            "href": "https://issues.apache.org/jira/projects/SYNCOPE"
          }
        }
      },
      {
        "issue": "SYNCOPE-1885",
        "title": "Self password reset does not trigger notification tasks without Flowable extension",
        "type": "Improvement",
        "_links": {
          "curies": [
            {
              "name": "int",
              "href": "https://www.danklco.com/api-docs/rels.html#{rel}",
              "templated": true
            },
            {
              "name": "jira",
              "href": "https://www.danklco.com/api-docs/rels.html#{rel}",
              "templated": true
            },
            {
              "name": "proj",
              "href": "https://www.danklco.com/api-docs/rels.html#{rel}",
              "templated": true
            }
          ],
          "int:release": {
            "title": "The release containing this issue",
            "href": "https://apis.danklco.com/apache-release-info/SYNCOPE/12355760"
          },
          "int:project": {
            "title": "The project containing this issue",
            "href": "https://apis.danklco.com/apache-release-info/SYNCOPE"
          },
          "int:root": {
            "title": "The root of this API",
            "href": "https://apis.danklco.com/apache-release-info/"
          },
          "jira:issue": {
            "title": "The issue in ASF Jira",
            "href": "https://issues.apache.org/jira/browse/SYNCOPE-1885"
          },
          "jira:release": {
            "title": "The release containing this issue in ASF Jira",
            "href": "https://issues.apache.org/jira/browse/SYNCOPE/fixforversion/12355760"
          },
          "jira:project": {
            "title": "The project containing this issue in ASF Jira",
            "href": "https://issues.apache.org/jira/projects/SYNCOPE"
          }
        }
      },
      {
        "issue": "SYNCOPE-1866",
        "title": "Implement AuthProfile management in Enduser",
        "type": "Task",
        "_links": {
          "curies": [
            {
              "name": "int",
              "href": "https://www.danklco.com/api-docs/rels.html#{rel}",
              "templated": true
            },
            {
              "name": "jira",
              "href": "https://www.danklco.com/api-docs/rels.html#{rel}",
              "templated": true
            },
            {
              "name": "proj",
              "href": "https://www.danklco.com/api-docs/rels.html#{rel}",
              "templated": true
            }
          ],
          "int:release": {
            "title": "The release containing this issue",
            "href": "https://apis.danklco.com/apache-release-info/SYNCOPE/12355760"
          },
          "int:project": {
            "title": "The project containing this issue",
            "href": "https://apis.danklco.com/apache-release-info/SYNCOPE"
          },
          "int:root": {
            "title": "The root of this API",
            "href": "https://apis.danklco.com/apache-release-info/"
          },
          "jira:issue": {
            "title": "The issue in ASF Jira",
            "href": "https://issues.apache.org/jira/browse/SYNCOPE-1866"
          },
          "jira:release": {
            "title": "The release containing this issue in ASF Jira",
            "href": "https://issues.apache.org/jira/browse/SYNCOPE/fixforversion/12355760"
          },
          "jira:project": {
            "title": "The project containing this issue in ASF Jira",
            "href": "https://issues.apache.org/jira/projects/SYNCOPE"
          }
        }
      },
      {
        "issue": "SYNCOPE-1876",
        "title": "Remove Virtual Attributes",
        "type": "Task",
        "_links": {
          "curies": [
            {
              "name": "int",
              "href": "https://www.danklco.com/api-docs/rels.html#{rel}",
              "templated": true
            },
            {
              "name": "jira",
              "href": "https://www.danklco.com/api-docs/rels.html#{rel}",
              "templated": true
            },
            {
              "name": "proj",
              "href": "https://www.danklco.com/api-docs/rels.html#{rel}",
              "templated": true
            }
          ],
          "int:release": {
            "title": "The release containing this issue",
            "href": "https://apis.danklco.com/apache-release-info/SYNCOPE/12355760"
          },
          "int:project": {
            "title": "The project containing this issue",
            "href": "https://apis.danklco.com/apache-release-info/SYNCOPE"
          },
          "int:root": {
            "title": "The root of this API",
            "href": "https://apis.danklco.com/apache-release-info/"
          },
          "jira:issue": {
            "title": "The issue in ASF Jira",
            "href": "https://issues.apache.org/jira/browse/SYNCOPE-1876"
          },
          "jira:release": {
            "title": "The release containing this issue in ASF Jira",
            "href": "https://issues.apache.org/jira/browse/SYNCOPE/fixforversion/12355760"
          },
          "jira:project": {
            "title": "The project containing this issue in ASF Jira",
            "href": "https://issues.apache.org/jira/projects/SYNCOPE"
          }
        }
      },
      {
        "issue": "SYNCOPE-1877",
        "title": "Include SAML SP keystore and metadata in AuthModule configuration",
        "type": "Task",
        "_links": {
          "curies": [
            {
              "name": "int",
              "href": "https://www.danklco.com/api-docs/rels.html#{rel}",
              "templated": true
            },
            {
              "name": "jira",
              "href": "https://www.danklco.com/api-docs/rels.html#{rel}",
              "templated": true
            },
            {
              "name": "proj",
              "href": "https://www.danklco.com/api-docs/rels.html#{rel}",
              "templated": true
            }
          ],
          "int:release": {
            "title": "The release containing this issue",
            "href": "https://apis.danklco.com/apache-release-info/SYNCOPE/12355760"
          },
          "int:project": {
            "title": "The project containing this issue",
            "href": "https://apis.danklco.com/apache-release-info/SYNCOPE"
          },
          "int:root": {
            "title": "The root of this API",
            "href": "https://apis.danklco.com/apache-release-info/"
          },
          "jira:issue": {
            "title": "The issue in ASF Jira",
            "href": "https://issues.apache.org/jira/browse/SYNCOPE-1877"
          },
          "jira:release": {
            "title": "The release containing this issue in ASF Jira",
            "href": "https://issues.apache.org/jira/browse/SYNCOPE/fixforversion/12355760"
          },
          "jira:project": {
            "title": "The project containing this issue in ASF Jira",
            "href": "https://issues.apache.org/jira/projects/SYNCOPE"
          }
        }
      }
    ]
  }
}